{
  "recipes": {
    "772e2f6e7d048c68d44ece141143ea32": {
      "name": "Code Review",
      "path": "/Users/mini/code/wingman/recipes/user/772e2f6e7d048c68d44ece141143ea32.json",
      "createdAt": "2025-08-19T02:17:40.577Z"
    },
    "7c7583b29306b0cee9edb8bcda89e9d2": {
      "name": "Planner",
      "path": "/Users/mini/code/wingman/recipes/user/7c7583b29306b0cee9edb8bcda89e9d2.json",
      "createdAt": "2025-08-19T04:31:15.392Z",
      "updatedAt": "2025-08-19T07:33:30.197Z"
    },
    "76b7444d2a354632e36185e7c972754d": {
      "name": "NEW",
      "path": "/Users/mini/code/wingman/.worktrees/rcp/recipes/user/76b7444d2a354632e36185e7c972754d.json",
      "createdAt": "2025-08-19T07:08:10.018Z"
    }
  },
  "usage": {
    "7c7583b29306b0cee9edb8bcda89e9d2": {
      "count": 9,
      "sessions": [
        {
          "sessionId": "recipe-Planner-1755577954767",
          "timestamp": "2025-08-19T04:32:34.778Z"
        },
        {
          "sessionId": "new",
          "timestamp": "2025-08-19T05:54:18.083Z"
        },
        {
          "sessionId": "new",
          "timestamp": "2025-08-19T06:04:57.171Z"
        },
        {
          "sessionId": "new",
          "timestamp": "2025-08-19T06:52:22.684Z"
        },
        {
          "sessionId": "Recipe",
          "timestamp": "2025-08-19T07:07:06.587Z"
        },
        {
          "sessionId": "new",
          "timestamp": "2025-08-19T07:17:57.510Z"
        },
        {
          "sessionId": "Does Work",
          "timestamp": "2025-08-19T07:22:10.156Z"
        },
        {
          "sessionId": "rec-check",
          "timestamp": "2025-08-19T07:30:42.167Z"
        },
        {
          "sessionId": "New Recipe Planner",
          "timestamp": "2025-08-19T07:50:30.477Z"
        }
      ],
      "firstUsed": "2025-08-19T04:32:34.778Z",
      "lastUsed": "2025-08-19T07:50:30.477Z"
    },
    "772e2f6e7d048c68d44ece141143ea32": {
      "count": 1,
      "sessions": [
        {
          "sessionId": "withrec",
          "timestamp": "2025-08-19T06:53:05.889Z"
        }
      ],
      "firstUsed": "2025-08-19T06:53:05.889Z",
      "lastUsed": "2025-08-19T06:53:05.889Z"
    },
    "76b7444d2a354632e36185e7c972754d": {
      "count": 2,
      "sessions": [
        {
          "sessionId": "NEW",
          "timestamp": "2025-08-19T07:08:42.752Z"
        },
        {
          "sessionId": "recipe",
          "timestamp": "2025-08-19T07:16:37.745Z"
        }
      ],
      "firstUsed": "2025-08-19T07:08:42.752Z",
      "lastUsed": "2025-08-19T07:16:37.745Z"
    }
  },
  "lastUpdated": "2025-08-16T05:54:11.930Z"
}